ure/__init__.py
ure/__version__.py
ure/extra.py
ure/peg.py
ure-0.1.dist-info/METADATA
ure-0.1.dist-info/WHEEL
ure-0.1.dist-info/licenses/LICENSE
ure-0.1.dist-info/licenses/LICENSE.txt
ure-0.1.dist-info/RECORD
