Metadata-Version: 2.3
Name: ure
Version: 0.1
Summary: universal regular expressions
Project-URL: Documentation, https://github.com/aleivag/ure#readme
Project-URL: Issues, https://github.com/aleivag/ure/issues
Project-URL: Source, https://github.com/aleivag/ure
Author-email: Alvaro Leiva <aleivag@gmail.com>
License: MIT License
Classifier: License :: OSI Approved :: MIT License
Classifier: Operating System :: OS Independent
Classifier: Programming Language :: Python :: 3
